<?xml version="1.0" encoding="Shift_JIS"?>

<event version="2.0">
    <sequence name="FARONWOP">
        <staff name="CAMERA">
            <cut name="FIXEDFRM">
                <data name="Center" type="XYZ">-14700.435 920.864 5909.221</data>
                <data name="Eye" type="XYZ">-14394.053 831.116 5944.239</data>
                <data name="Fovy" type="FLOAT">65.000</data>
                <data name="Timer" type="INTEGER">70</data>
                <data name="BGCheck" type="INTEGER">3</data>
            </cut>
            <cut name="BSPTRANS">
                <data name="Center" type="XYZ">-14635.074 652.107 5867.240</data>
                <data name="Eye" type="XYZ">-14418.077 661.574 6103.863</data>
                <data name="Fovy" type="FLOAT">58.000</data>
                <data name="Timer" type="INTEGER">110</data>
                <data name="BGCheck" type="INTEGER">3</data>
                <data name="Base" type="FLOAT">
                    0.000
                    0.000
                    0.100
                    0.300
                    0.600
                    1.000
                    1.000
                </data>
                <data name="Use1" type="STRING">oxxoxx</data>
                <data name="Set1" type="FLOAT">
                    0.000
                    0.000
                    1.000
                    1.000
                    1.000
                </data>
            </cut>
            <cut name="FIXEDFRM">
                <data name="RelActor" type="STRING">@PLAYER</data>
                <data name="Center" type="XYZ">0.000 5.000 0.000</data>
                <data name="Eye" type="XYZ">0.000 90.000 -545.000</data>
                <data name="Timer" type="INTEGER">10</data>
                <data name="Fovy" type="FLOAT">60.000</data>
            </cut>
        </staff>
        <staff name="TIMEKEEPER">
            <cut name="WAIT">
            </cut>
            <cut name="COUNTDOWN">
                <data name="Timer" type="INTEGER">20</data>
            </cut>
            <cut name="COUNTDOWN">
                <data name="Timer" type="INTEGER">10</data>
            </cut>
        </staff>
        <staff name="Link">
            <cut name="001n_wait">
            </cut>
            <cut name="003n_dash">
                <data name="pos" type="XYZ">-15191.772 213.243 4721.110</data>
                <data name="stick" type="FLOAT">0.750</data>
            </cut>
        </staff>
        <staff name="Horse">
            <cut name="005iwait">
                <data name="ride" type="INTEGER">1</data>
                <data name="pos" type="XYZ">-15503.219 891.102 7920.009</data>
                <data name="angle" type="INTEGER">-32436</data>
            </cut>
            <cut name="002walk">
                <data name="ride" type="INTEGER">1</data>
                <data name="pos" type="XYZ">-15191.772 213.243 4721.110</data>
            </cut>
        </staff>
        <staff name="MESSAGE">
            <cut name="WAIT">
            </cut>
            <cut name="TELOP">
            </cut>
        </staff>
        <staff name="ALL">
            <cut name="dummy">
            </cut>
        </staff>
    </sequence>
    <sequence name="FARONWOP$0">
        <staff name="Link">
            <cut name="004init_wait">
                <data name="pos" type="XYZ">-15192.178 213.239 4724.416</data>
                <data name="angle" type="INTEGER">31521</data>
                <data name="prm0" type="INTEGER">6</data>
            </cut>
        </staff>
        <staff name="CAMERA">
            <cut name="WAIT">
            </cut>
            <cut name="FIXEDFRM">
                <data name="RelActor" type="STRING">@PLAYER</data>
                <data name="Center" type="XYZ">0.000 -20.000 0.000</data>
                <data name="Eye" type="XYZ">0.000 80.000 -360.000</data>
                <data name="Timer" type="INTEGER">1</data>
                <data name="Fovy" type="FLOAT">60.000</data>
            </cut>
        </staff>
    </sequence>
    <sequence name="demo04_01">
        <staff name="PACKAGE">
            <cut name="PLAY">
                <data name="FileName" type="STRING">demo04_01.stb</data>
            </cut>
            <cut name="WAIT">
            </cut>
        </staff>
        <staff name="CAMERA">
            <cut name="STBWAIT">
                <data name="BGCheck" type="INTEGER">3</data>
            </cut>
        </staff>
        <staff name="DIRECTOR">
            <cut name="MAPTOOL">
                <data name="ID" type="INTEGER">0</data>
            </cut>
        </staff>
        <staff name="ALL">
            <cut name="DUMMY">
            </cut>
        </staff>
    </sequence>
    <sequence name="demo09_01">
        <staff name="PACKAGE">
            <cut name="PLAY">
                <data name="FileName" type="STRING">demo09_01.stb</data>
            </cut>
            <cut name="WAIT">
            </cut>
        </staff>
        <staff name="CAMERA">
            <cut name="STBWAIT">
                <data name="BGCheck" type="INTEGER">3</data>
            </cut>
        </staff>
        <staff name="DIRECTOR">
            <cut name="MAPTOOL">
                <data name="ID" type="INTEGER">8</data>
            </cut>
        </staff>
        <staff name="ALL">
            <cut name="DUMMY">
            </cut>
        </staff>
    </sequence>
    <sequence name="demo10">
        <staff name="PACKAGE">
            <cut name="PLAY">
                <data name="FileName" type="STRING">demo10.stb</data>
            </cut>
            <cut name="WAIT">
            </cut>
        </staff>
        <staff name="CAMERA">
            <cut name="STBWAIT">
                <data name="BGCheck" type="INTEGER">3</data>
            </cut>
        </staff>
        <staff name="DIRECTOR">
            <cut name="MAPTOOL">
                <data name="ID" type="INTEGER">9</data>
            </cut>
        </staff>
        <staff name="ALL">
            <cut name="DUMMY">
            </cut>
        </staff>
    </sequence>
    <sequence name="start_ff03">
        <staff name="PACKAGE">
            <cut name="PLAY">
                <data name="FileName" type="STRING">start_ff03.stb</data>
            </cut>
            <cut name="WAIT">
            </cut>
        </staff>
        <staff name="CAMERA">
            <cut name="STBWAIT">
                <data name="BGCheck" type="INTEGER">3</data>
            </cut>
        </staff>
        <staff name="DIRECTOR">
            <cut name="MAPTOOL">
                <data name="ID" type="INTEGER">18</data>
            </cut>
        </staff>
        <staff name="ALL">
            <cut name="DUMMY">
            </cut>
        </staff>
    </sequence>
    <sequence name="demo24_03">
        <staff name="PACKAGE">
            <cut name="PLAY">
                <data name="FileName" type="STRING">demo24_03.stb</data>
            </cut>
            <cut name="WAIT">
            </cut>
        </staff>
        <staff name="CAMERA">
            <cut name="STBWAIT">
                <data name="BGCheck" type="INTEGER">3</data>
            </cut>
        </staff>
        <staff name="DIRECTOR">
            <cut name="MAPTOOL">
                <data name="ID" type="INTEGER">20</data>
            </cut>
        </staff>
        <staff name="ALL">
            <cut name="DUMMY">
            </cut>
        </staff>
    </sequence>
</event>
